vortex_python_sdk-0.1.3.dist-info/licenses/LICENSE
vortex_sdk/__init__.py
vortex_sdk/py.typed
vortex_sdk/types.py
vortex_sdk/vortex.py
vortex_python_sdk-0.1.3.dist-info/METADATA
vortex_python_sdk-0.1.3.dist-info/WHEEL
vortex_python_sdk-0.1.3.dist-info/top_level.txt
vortex_python_sdk-0.1.3.dist-info/RECORD
