Metadata-Version: 2.4
Name: vortex-python-sdk
Version: 0.1.3
Summary: Vortex Python SDK for invitation management and JWT generation
Author-email: TeamVortexSoftware <support@vortexsoftware.com>
License-Expression: MIT
Project-URL: Homepage, https://github.com/teamvortexsoftware/vortex-python-sdk
Project-URL: Repository, https://github.com/teamvortexsoftware/vortex-python-sdk.git
Project-URL: Documentation, https://docs.vortexsoftware.com/python-sdk
Project-URL: Changelog, https://github.com/teamvortexsoftware/vortex-python-sdk/blob/main/CHANGELOG.md
Keywords: vortex,invitations,jwt,api,sdk
Classifier: Development Status :: 4 - Beta
Classifier: Intended Audience :: Developers
Classifier: Operating System :: OS Independent
Classifier: Programming Language :: Python :: 3
Classifier: Programming Language :: Python :: 3.8
Classifier: Programming Language :: Python :: 3.9
Classifier: Programming Language :: Python :: 3.10
Classifier: Programming Language :: Python :: 3.11
Classifier: Programming Language :: Python :: 3.12
Classifier: Programming Language :: Python :: 3.13
Classifier: Topic :: Software Development :: Libraries :: Python Modules
Requires-Python: >=3.8
License-File: LICENSE
Requires-Dist: httpx>=0.27.0
Requires-Dist: pydantic>=2.8.0
Requires-Dist: typing-extensions>=4.8.0
Provides-Extra: dev
Requires-Dist: pytest>=7.0.0; extra == "dev"
Requires-Dist: pytest-asyncio>=0.21.0; extra == "dev"
Requires-Dist: pytest-cov>=4.0.0; extra == "dev"
Requires-Dist: black>=23.0.0; extra == "dev"
Requires-Dist: isort>=5.12.0; extra == "dev"
Requires-Dist: mypy>=1.0.0; extra == "dev"
Requires-Dist: ruff>=0.1.0; extra == "dev"
Dynamic: license-file
